{
    "ColumnConfig": {
        "ModalSCCCMO093144": {
            "title": "\\列定制面板\\"
        },
        "TabPaneSCCCMO836557": {
            "label": "\\基本配置\\"
        },
        "PanelSCCCMO096371": {
            "innerContent": "引用设置"
        },
        "pSCCCMO519045": {
            "innerContent": "引用类"
        },
        "el-option-groupSCCCMO785769": {
            "label": "\\实体类\\"
        },
        "el-option-groupSCCCMO832268": {
            "label": "\\外部实体类\\"
        },
        "el-option-groupSCCCMO167600": {
            "label": "\\关联类\\"
        },
        "pSCCCMO973143": {
            "innerContent": "回填字段（引用类中对应的属性）"
        },
        "el-option-groupSCCCMO649882": {
            "label": "\\系统属性\\"
        },
        "el-option-groupSCCCMO758737": {
            "label": "\\类属性\\"
        },
        "el-option-groupSCCCMO264346": {
            "label": "\\关联类系统属性\\"
        },
        "el-option-groupSCCCMO717643": {
            "label": "\\关联类属性\\"
        },
        "pSCCCMO580899": {
            "innerContent": "浏览字段（最后显示到表格的属性）"
        },
        "el-option-groupSCCCMO439685": {
            "label": "\\系统属性\\"
        },
        "el-option-groupSCCCMO921812": {
            "label": "\\类属性\\"
        },
        "el-option-groupSCCCMO026227": {
            "label": "\\关联类系统属性\\"
        },
        "el-option-groupSCCCMO727108": {
            "label": "\\关联类属性\\"
        },
        "pSCCCMO584975": {
            "innerContent": "过滤条件"
        },
        "InputSCCCMO146171": {
            "placeholder": "\\输入过滤条件\\"
        },
        "PanelSCCCMO322134": {
            "innerContent": "样式设置"
        },
        "spanSCCCMO574884": {
            "innerContent": "列宽"
        },
        "spanSCCCMO033920": {
            "innerContent": "列宽"
        },
        "TabPaneSCCCMO137339": {
            "label": "\\显示模式\\"
        },
        "SelectSCCCMO286997": {
            "placeholder": "\\请选择日期格式\\"
        },
        "OptionSCCCMO247495": {
            "label": "\\年月日\\"
        },
        "spanSCCCMO424821": {
            "innerContent": "年月日"
        },
        "OptionSCCCMO487161": {
            "label": "\\时分秒\\"
        },
        "spanSCCCMO789147": {
            "innerContent": "时分秒"
        },
        "OptionSCCCMO639785": {
            "label": "\\年月日时分秒\\"
        },
        "spanSCCCMO352514": {
            "innerContent": "年月日时分秒"
        }
    }
}